aclib/pyi/__init__.py
aclib/pyi/__API__/colorstr.py
aclib/pyi/__API__/compiler.py
aclib/pyi/__API__/const.py
aclib/pyi/__API__/installer.py
aclib_pyi-1.1.3.dist-info/licenses/LICENSE
aclib_pyi-1.1.3.dist-info/METADATA
aclib_pyi-1.1.3.dist-info/WHEEL
aclib_pyi-1.1.3.dist-info/top_level.txt
aclib_pyi-1.1.3.dist-info/RECORD
